django_mobi2-1.0.2.dist-info/METADATA
django_mobi2-1.0.2.dist-info/RECORD
django_mobi2-1.0.2.dist-info/WHEEL
django_mobi2-1.0.2.dist-info/top_level.txt
mobi2/__init__.py
mobi2/decorators.py
mobi2/middleware.py
mobi2/search_strings.txt
mobi2/tablet_strings.txt
mobi2/useragents.py
