Metadata-Version: 2.1
Name: django-mobi2
Version: 1.0.2
Summary: Django middleware and view decorator to detect phones and small-screen devices
Home-page: https://github.com/django-xxx/django-mobi2.git
Author: Hackathon
Author-email: kimi.huang@brightcells.com
License: UNKNOWN
Keywords: Django UserAgent
Platform: UNKNOWN
Classifier: Development Status :: 5 - Production/Stable
Classifier: Environment :: Web Environment
Classifier: Framework :: Django
Classifier: Intended Audience :: Developers
Classifier: Programming Language :: Python
Classifier: Topic :: Software Development :: Libraries :: Python Modules
Classifier: Topic :: Office/Business :: Financial :: Spreadsheet
Requires-Dist: django-six
